bjec/__init__.py
bjec/build.py
bjec/cli.py
bjec/collector.py
bjec/config.py
bjec/generator.py
bjec/job.py
bjec/master.py
bjec/params.py
bjec/processor.py
bjec/runner.py
bjec/subprocess_run.py
bjec/utils.py
bjec-0.2.8.dist-info/DESCRIPTION.rst
bjec-0.2.8.dist-info/METADATA
bjec-0.2.8.dist-info/RECORD
bjec-0.2.8.dist-info/WHEEL
bjec-0.2.8.dist-info/entry_points.txt
bjec-0.2.8.dist-info/metadata.json
bjec-0.2.8.dist-info/top_level.txt
