Metadata-Version: 2.0
Name: bjec
Version: 0.2.8
Summary: Batch Job Executor & Collector
Home-page: UNKNOWN
Author: UNKNOWN
Author-email: UNKNOWN
License: UNKNOWN
Platform: UNKNOWN
Requires-Dist: argh
Requires-Dist: gitpython
Requires-Dist: pyyaml
